Corrfunc/__init__.py
Corrfunc/_countpairs.cpython-37m-darwin.so
Corrfunc/_countpairs_mocks.cpython-37m-darwin.so
Corrfunc/bases.py
Corrfunc/call_correlation_functions.py
Corrfunc/call_correlation_functions_mocks.py
Corrfunc/io.py
Corrfunc/tests.py
Corrfunc/utils.py
Corrfunc/mocks/DDrppi_mocks.py
Corrfunc/mocks/DDsmu_mocks.py
Corrfunc/mocks/DDtheta_mocks.py
Corrfunc/mocks/__init__.py
Corrfunc/mocks/vpf_mocks.py
Corrfunc/theory/DD.py
Corrfunc/theory/DDrppi.py
Corrfunc/theory/DDsmu.py
Corrfunc/theory/__init__.py
Corrfunc/theory/vpf.py
Corrfunc/theory/wp.py
Corrfunc/theory/xi.py
mocks/tests/Mr19_mock.DD
mocks/tests/Mr19_mock.DR
mocks/tests/Mr19_mock_DDsmu.DR
mocks/tests/Mr19_mock_DDsmu.RR
mocks/tests/Mr19_mock_vpf
mocks/tests/Mr19_mock_wtheta.DD
mocks/tests/Mr19_mock_wtheta.DR
mocks/tests/Mr19_randoms_vpf
mocks/tests/angular_bins
mocks/tests/bins
mocks/tests/data/Mr19_centers_xyz_forVPF_rmax_10Mpc.txt
mocks/tests/data/Mr19_mock_northonly.rdcz.dat
mocks/tests/data/Mr19_mock_northonly.rdcz.ff
mocks/tests/data/Mr19_randoms_northonly.rdcz.ff
theory/tests/Mr19_DD_nonperiodic
theory/tests/Mr19_DD_periodic
theory/tests/Mr19_DDrppi_nonperiodic
theory/tests/Mr19_DDrppi_periodic
theory/tests/Mr19_DDsmu_nonperiodic
theory/tests/Mr19_DDsmu_periodic
theory/tests/Mr19_vpf_periodic
theory/tests/Mr19_wp
theory/tests/Mr19_xi
theory/tests/bins
theory/tests/cmass_DD_periodic
theory/tests/cmass_DR_nonperiodic
theory/tests/cmass_DR_periodic
theory/tests/cmass_RR_periodic
theory/tests/data/cat_L750_n1e-4_lognormal_rlz0.bin
theory/tests/data/cat_L750_n1e-4_z057_patchy_lognormal_rlz0.bin
theory/tests/data/cat_L750_n2e-4_z057_patchy_lognormal_rlz0.bin
theory/tests/data/cat_L750_n3e-4_lognormal_rlz0.bin
theory/tests/data/cat_L750_n5e-5_z057_patchy_lognormal_rlz0.bin
theory/tests/data/cmassmock_Zspace.ff
theory/tests/data/gals_Mr19.ff
theory/tests/data/random_Zspace.ff
suave-0.0.6.dist-info/LICENSE
suave-0.0.6.dist-info/METADATA
suave-0.0.6.dist-info/WHEEL
suave-0.0.6.dist-info/top_level.txt
suave-0.0.6.dist-info/RECORD
