Metadata-Version: 2.1
Name: suave
Version: 0.0.6
Summary: A continuous-function estimator for 2-point statistics
Home-page: https://github.com/kstoreyf/suave
Author: Kate Storey-Fisher
Author-email: kstoreyfisher@gmail.com
Maintainer: Kate Storey-Fisher
Maintainer-email: kstoreyfisher@gmail.com
License: MIT
Download-URL: https://github.com/kstoreyf/suave/archive/suave-0.0.6.tar.gz
Keywords: correlation functions,simulations,surveys,galaxies
Platform: Linux
Platform: Mac OSX
Platform: Unix
Classifier: Development Status :: 4 - Beta
Classifier: Intended Audience :: Developers
Classifier: Intended Audience :: Science/Research
Classifier: License :: OSI Approved :: MIT License
Classifier: Natural Language :: English
Classifier: Operating System :: POSIX
Classifier: Programming Language :: C
Classifier: Programming Language :: Python
Classifier: Programming Language :: Python :: 2
Classifier: Programming Language :: Python :: 2.7
Classifier: Programming Language :: Python :: 3
Classifier: Programming Language :: Python :: 3.4
Classifier: Programming Language :: Python :: 3.5
Classifier: Programming Language :: Python :: 3.6
Provides: suave
Requires-Python: >=2.7, !=3.0.*, !=3.1.*, !=3.2.*, !=3.3.*, <4
Requires-Dist: numpy (>=1.7)
Requires-Dist: future
Requires-Dist: wurlitzer
Requires-Dist: scipy
Requires-Dist: colossus
Requires-Dist: six
